[
    {
        "tema": "javier milei",
        "frecuencia": 35
    },
    {
        "tema": "corte supremo",
        "frecuencia": 12
    },
    {
        "tema": "casa rosado",
        "frecuencia": 12
    },
    {
        "tema": "manuel adorni",
        "frecuencia": 10
    },
    {
        "tema": "red social",
        "frecuencia": 9
    },
    {
        "tema": "vocero presidencial",
        "frecuencia": 9
    },
    {
        "tema": "derechos humanos",
        "frecuencia": 9
    },
    {
        "tema": "habitual conferencia",
        "frecuencia": 8
    },
    {
        "tema": "alberto fernández",
        "frecuencia": 7
    },
    {
        "tema": "río cuarto",
        "frecuencia": 7
    },
    {
        "tema": "luis caputo",
        "frecuencia": 6
    },
    {
        "tema": "libertad avanzo",
        "frecuencia": 6
    },
    {
        "tema": "capital humano",
        "frecuencia": 5
    },
    {
        "tema": "superávit financiero",
        "frecuencia": 4
    },
    {
        "tema": "crisis económico",
        "frecuencia": 4
    },
    {
        "tema": "sesión especial",
        "frecuencia": 4
    },
    {
        "tema": "fuerza armado",
        "frecuencia": 4
    },
    {
        "tema": "atentado político",
        "frecuencia": 3
    },
    {
        "tema": "martín llaryoro",
        "frecuencia": 3
    },
    {
        "tema": "gestión libertario",
        "frecuencia": 3
    }
]